{
  "hash": "9a8757da",
  "configHash": "9176b415",
  "lockfileHash": "9e9d82b4",
  "browserHash": "590964ca",
  "optimized": {
    "react": {
      "src": "../../node_modules/react/index.js",
      "file": "react.js",
      "fileHash": "5430bae7",
      "needsInterop": true
    },
    "react-dom/client": {
      "src": "../../node_modules/react-dom/client.js",
      "file": "react-dom_client.js",
      "fileHash": "6ae3e510",
      "needsInterop": true
    }
  },
  "chunks": {
    "chunk-Y7MCAJS7": {
      "file": "chunk-Y7MCAJS7.js"
    }
  }
}